dg_tta/__build__.py
dg_tta/__init__.py
dg_tta/__resources__/TS104_input_view.png
dg_tta/__resources__/check_tta_input.ipynb
dg_tta/__resources__/dummy_results/nnUNetTrainer_GIN_MIND_MultiRes__nnUNetPlans__3d_fullres/dataset.json
dg_tta/__resources__/dummy_results/nnUNetTrainer_GIN_MIND_MultiRes__nnUNetPlans__3d_fullres/dataset_fingerprint.json
dg_tta/__resources__/dummy_results/nnUNetTrainer_GIN_MIND_MultiRes__nnUNetPlans__3d_fullres/plans.json
dg_tta/__resources__/dummy_results/nnUNetTrainer_GIN_MIND__nnUNetPlans__3d_fullres/dataset.json
dg_tta/__resources__/dummy_results/nnUNetTrainer_GIN_MIND__nnUNetPlans__3d_fullres/dataset_fingerprint.json
dg_tta/__resources__/dummy_results/nnUNetTrainer_GIN_MIND__nnUNetPlans__3d_fullres/plans.json
dg_tta/__resources__/dummy_results/nnUNetTrainer_GIN_MultiRes__nnUNetPlans__3d_fullres/dataset.json
dg_tta/__resources__/dummy_results/nnUNetTrainer_GIN_MultiRes__nnUNetPlans__3d_fullres/dataset_fingerprint.json
dg_tta/__resources__/dummy_results/nnUNetTrainer_GIN_MultiRes__nnUNetPlans__3d_fullres/plans.json
dg_tta/__resources__/dummy_results/nnUNetTrainer_GIN__nnUNetPlans__3d_fullres/dataset.json
dg_tta/__resources__/dummy_results/nnUNetTrainer_GIN__nnUNetPlans__3d_fullres/dataset_fingerprint.json
dg_tta/__resources__/dummy_results/nnUNetTrainer_GIN__nnUNetPlans__3d_fullres/plans.json
dg_tta/__resources__/dummy_results/nnUNetTrainer_MIND_MultiRes__nnUNetPlans__3d_fullres/dataset.json
dg_tta/__resources__/dummy_results/nnUNetTrainer_MIND_MultiRes__nnUNetPlans__3d_fullres/dataset_fingerprint.json
dg_tta/__resources__/dummy_results/nnUNetTrainer_MIND_MultiRes__nnUNetPlans__3d_fullres/plans.json
dg_tta/__resources__/dummy_results/nnUNetTrainer_MIND__nnUNetPlans__3d_fullres/dataset.json
dg_tta/__resources__/dummy_results/nnUNetTrainer_MIND__nnUNetPlans__3d_fullres/dataset_fingerprint.json
dg_tta/__resources__/dummy_results/nnUNetTrainer_MIND__nnUNetPlans__3d_fullres/plans.json
dg_tta/gin.py
dg_tta/mind.py
dg_tta/pretraining/__init__.py
dg_tta-1.0.18.dist-info/LICENSE
dg_tta-1.0.18.dist-info/METADATA
dg_tta-1.0.18.dist-info/WHEEL
dg_tta-1.0.18.dist-info/entry_points.txt
dg_tta-1.0.18.dist-info/RECORD
