Metadata-Version: 2.1
Name: dg-tta
Version: 1.0.18
Summary: DG-TTA: Out-of-domain medical image segmentation through Domain Generalization and Test-Time Adaptation
Author: Christian Weihsbach
Author-email: christian.weihsbach@uni-luebeck.de
Requires-Python: >=3.9,<4.0
Classifier: Programming Language :: Python :: 3
Classifier: Programming Language :: Python :: 3.9
Classifier: Programming Language :: Python :: 3.10
Classifier: Programming Language :: Python :: 3.11
Requires-Dist: ipykernel (>=6.27.1,<7.0.0)
Requires-Dist: nnunetv2 (>=2.2.1,<3.0.0)
Requires-Dist: randomname (>=0.2.1,<0.3.0)
Requires-Dist: wandb (>=0.16.1,<0.17.0)
